{
    "id": 100, 
    "step": 11,
    "title": "Britisches Weltreich",
    "subtitle": "Größtes Kolonialreich der Geschichte",
    "titleImage": "/images/geschichte_britanien.jpg",
    "audio": "",
    "contents": [
        { 
            "body": "<h2>Unschlagbare Marine</h2>\n<p>\nDas Britische Weltreich war vom 17. bis 20. Jh das größte, bestehende Kolonialreich\nder Geschichte und vom Ende der Napoleonischen Ära bis zum 1. WK die führende\nWeltmacht (Victorianische Epoche / Queen Victoria).\n</p>\n\n\n" 
        }
    ]
   
}